exoscale_auth.py
requests_exoscale_auth-1.1.2.dist-info/LICENSE
requests_exoscale_auth-1.1.2.dist-info/METADATA
requests_exoscale_auth-1.1.2.dist-info/WHEEL
requests_exoscale_auth-1.1.2.dist-info/top_level.txt
requests_exoscale_auth-1.1.2.dist-info/RECORD
