Metadata-Version: 2.1
Name: requests-exoscale-auth
Version: 1.1.2
Summary: Exoscale APIs support for Python-Requests.
Home-page: https://github.com/exoscale/requests-exoscale-auth
Author: Exoscale
Author-email: contact@exoscale.com
License: BSD
Platform: any
Classifier: Intended Audience :: Developers
Classifier: Intended Audience :: System Administrators
Classifier: License :: OSI Approved :: BSD License
Classifier: Operating System :: OS Independent
Classifier: Programming Language :: Python
Classifier: Programming Language :: Python :: 3
Requires-Dist: requests
